[{"column_name": "address_id", "column_type": "BIGINT", "null": "YES", "key": null, "default": null, "extra": null}, {"column_name": "building_name", "column_type": "VARCHAR", "null": "YES", "key": null, "default": null, "extra": null}, {"column_name": "street_address", "column_type": "VARCHAR", "null": "YES", "key": null, "default": null, "extra": null}, {"column_name": "city", "column_type": "VARCHAR", "null": "YES", "key": null, "default": null, "extra": null}, {"column_name": "county", "column_type": "VARCHAR", "null": "YES", "key": null, "default": null, "extra": null}, {"column_name": "postcode", "column_type": "VARCHAR", "null": "YES", "key": null, "default": null, "extra": null}, {"column_name": "country", "column_type": "VARCHAR", "null": "YES", "key": null, "default": null, "extra": null}]